__init__.py
gateloop.py
gateloop-0.0.2.dist-info/LICENSE
gateloop-0.0.2.dist-info/METADATA
gateloop-0.0.2.dist-info/WHEEL
gateloop-0.0.2.dist-info/top_level.txt
gateloop-0.0.2.dist-info/RECORD
